Workbook

Sheet Instructions
B2: CLOTHING BRAND FINANCIAL & PRODUCTION OPERATING SYSTEM
B3: Panduan Operasional, Manajemen HPP, Struktur Pricing & Analisis Impas (BEP) Koleksi
B5: KODE WARNA SEL | D5: PANDUAN PENGISIAN & ATURAN PENGGUNAAN
B6: Sel Berwarna Kuning | D6: Sel Input Manual: Masukkan angka real biaya vendor, harga bahan, dan target margin Anda.
B7: Sel Putih / Abu-abu | D7: Sel Formula Otomatis: Dihitung langsung oleh spreadsheet. Jangan hapus atau ketik manual.
B8: Sel Berwarna Hijau | D8: Key Indicator / Output Kunci: Menampilkan rekomendasi harga, laba bersih, dan titik impas.
B10: ALUR KERJA PENGGUNAAN SPREADSHEET (SOP 5 LANGKAH)
B11: Langkah 1: Riset Vendor | C11: Buka sheet 'Vendor_Database'. Catat nama vendor bahan, konveksi jahit, sablon, aksesoris, dan kontak WA.
B12: Langkah 2: Hitung HPP Pokok | C12: Buka sheet 'HPP_Calculator'. Isi rincian kain, ongkos jahit, sablon, label, dan packaging per helai.
B13: Langkah 3: Atur Target Margin | C13: Tentukan target margin kotor (rekomendasi retail 60%-70% untuk D2C, dan 30%-40% untuk reseller).
B14: Langkah 4: Rancang Batch Rilis | C14: Buka sheet 'Batch_Planner'. Tentukan kuantiti rilis dan masukkan biaya tetap peluncuran (sample, foto, ads).
B15: Langkah 5: Pantau KPI Dashboard | C15: Buka sheet 'Dashboard' untuk memantau performa portofolio produk, total investasi, dan target titik impas.
B17: GLOSARIUM & DEFINISI METRIK FINANSIAL
B18: HPP (Cost of Goods Sold) | C18: Total biaya modal langsung yang melekat pada 1 helai baju (Kain + Jahit + Sablon + Aksesoris + Kemasan).
B19: Margin Kotor (Gross Margin %) | C19: Persentase keuntungan sebelum dipotong operasional tetap: (Harga Jual - HPP) / Harga Jual.
B20: Titik Impas (BEP Unit) | C20: Jumlah minimal helai pakaian yang wajib terjual habis agar modal awal batch kembali 100% tanpa rugi.
B21: Titik Impas (BEP Rupiah) | C21: Jumlah omzet minimal yang harus masuk ke rekening sebelum bisnis menghasilkan laba bersih.
B22: ROI (Return on Investment %) | C22: Tingkat pengembalian modal investasi peluncuran: (Proyeksi Laba Bersih / Total Investasi) x 100%.

Sheet Dashboard
B2: EXECUTIVE BRAND FINANCIAL DASHBOARD
B3: Ringkasan Eksekutif Kinerja Portofolio Produk & Proyeksi Batch Produksi
B5: SKU AKTIF | C5: RATA-RATA HPP | D5: AVG MARGIN RETAIL | E5: MODAL INVESTASI BATCH | F5: PROYEKSI OMZET (SOLD OUT) | G5: PROYEKSI LABA BERSIH
B6: =COUNTA(HPP_Calculator!C6:C10) | C6: =AVERAGE(HPP_Calculator!N6:N10) | D6: =AVERAGE(HPP_Calculator!R6:R10) | E6: =Batch_Planner!F22 | F6: =Batch_Planner!F27 | G6: =Batch_Planner!F28
B8: RINGKASAN HARGA & PROFITABILITAS PER PRODUK
B9: Nama Produk | C9: Kategori | D9: HPP Satuan | E9: Harga Retail | F9: Laba Kotor (Retail) | G9: Margin Retail Real
B10: =HPP_Calculator!C6 | C10: =HPP_Calculator!D6 | D10: =HPP_Calculator!N6 | E10: =HPP_Calculator!P6 | F10: =HPP_Calculator!Q6 | G10: =HPP_Calculator!R6
B11: =HPP_Calculator!C7 | C11: =HPP_Calculator!D7 | D11: =HPP_Calculator!N7 | E11: =HPP_Calculator!P7 | F11: =HPP_Calculator!Q7 | G11: =HPP_Calculator!R7
B12: =HPP_Calculator!C8 | C12: =HPP_Calculator!D8 | D12: =HPP_Calculator!N8 | E12: =HPP_Calculator!P8 | F12: =HPP_Calculator!Q8 | G12: =HPP_Calculator!R8
B13: =HPP_Calculator!C9 | C13: =HPP_Calculator!D9 | D13: =HPP_Calculator!N9 | E13: =HPP_Calculator!P9 | F13: =HPP_Calculator!Q9 | G13: =HPP_Calculator!R9
B14: =HPP_Calculator!C10 | C14: =HPP_Calculator!D10 | D14: =HPP_Calculator!N10 | E14: =HPP_Calculator!P10 | F14: =HPP_Calculator!Q10 | G14: =HPP_Calculator!R10
B16: ANALISIS SKENARIO PENJUALAN BATCH (STRESS TEST)
B17: Skenario Penjualan | C17: Tingkat Keterjualan | D17: Total Helai Terjual | E17: Total Omzet Masuk | F17: Laba / Rugi Bersih | G17: ROI Batch
B18: Skenario 1: Sold Out Penuh (Optimis) | C18: 1 | D18: =ROUND(Batch_Planner!D11*1.0, 0) | E18: =ROUND(Batch_Planner!F27*1.0, -2) | F18: =E18-Batch_Planner!F22 | G18: =ROUND((F18/Batch_Planner!F22)*100, 1)
B19: Skenario 2: Terjual 75% (Moderat) | C19: 0.75 | D19: =ROUND(Batch_Planner!D11*0.75, 0) | E19: =ROUND(Batch_Planner!F27*0.75, -2) | F19: =E19-Batch_Planner!F22 | G19: =ROUND((F19/Batch_Planner!F22)*100, 1)
B20: Skenario 3: Terjual 50% (Konservatif / Titik Impas) | C20: 0.5 | D20: =ROUND(Batch_Planner!D11*0.5, 0) | E20: =ROUND(Batch_Planner!F27*0.5, -2) | F20: =E20-Batch_Planner!F22 | G20: =ROUND((F20/Batch_Planner!F22)*100, 1)
B21: Skenario 4: Terjual 30% (Skenario Buruk) | C21: 0.3 | D21: =ROUND(Batch_Planner!D11*0.3, 0) | E21: =ROUND(Batch_Planner!F27*0.3, -2) | F21: =E21-Batch_Planner!F22 | G21: =ROUND((F21/Batch_Planner!F22)*100, 1)

Sheet HPP_Calculator
B2: KALKULATOR HPP & PENETAPAN HARGA MULTI-PRODUK (COST OF GOODS SOLD)
B3: Rincian Biaya Pokok Kain, Jahit, Sablon, Aksesoris, Kemasan & Struktur Pricing Retail/Reseller
B4: No | C4: Nama Produk | D4: Kategori | E4: Material Kain | F4: Biaya Bahan Kain | H4: Ongkos Jahit | I4: Sablon / Bordir | J4: Label & Hangtag | K4: Plastik Ziplock | L4: Polymailer Kurir | M4: QC & Finishing | N4: Total HPP Satuan | O4: Target Margin (%) | P4: Harga Retail | Q4: Laba Kotor Retail | R4: Margin Retail Real | S4: Harga Reseller | T4: Margin Reseller
F5: Harga/Kg/Yd | G5: Konsumsi
B6: 1 | C6: Boxy Heavy T-Shirt | D6: Kaos | E6: Combed 16s (240 gsm) | F6: 58000 | G6: 0.38 | H6: 16000 | I6: 13000 | J6: 2200 | K6: 2500 | L6: 800 | M6: 1500 | N6: =ROUND((F6*G6)+SUM(H6:M6), 0) | O6: 0.65 | P6: =ROUND(N6/(1-O6), -2) | Q6: =P6-N6 | R6: =Q6/P6 | S6: =ROUND(N6*1.35, -2) | T6: =(S6-N6)/S6
B7: 2 | C7: Classic Regular T-Shirt | D7: Kaos | E7: Combed 24s (180 gsm) | F7: 48000 | G7: 0.33 | H7: 14000 | I7: 11000 | J7: 2200 | K7: 2500 | L7: 800 | M7: 1200 | N7: =ROUND((F7*G7)+SUM(H7:M7), 0) | O7: 0.6 | P7: =ROUND(N7/(1-O7), -2) | Q7: =P7-N7 | R7: =Q7/P7 | S7: =ROUND(N7*1.35, -2) | T7: =(S7-N7)/S7
B8: 3 | C8: Pullover Heavy Hoodie | D8: Outerwear | E8: Cotton Fleece 330 gsm | F8: 85000 | G8: 0.85 | H8: 32000 | I8: 18000 | J8: 3000 | K8: 3500 | L8: 1200 | M8: 2500 | N8: =ROUND((F8*G8)+SUM(H8:M8), 0) | O8: 0.65 | P8: =ROUND(N8/(1-O8), -2) | Q8: =P8-N8 | R8: =Q8/P8 | S8: =ROUND(N8*1.35, -2) | T8: =(S8-N8)/S8
B9: 4 | C9: Worker Utility Overshirt | D9: Kemeja | E9: Baby Canvas Twill | F9: 42000 | G9: 1.4 | H9: 35000 | I9: 12000 | J9: 3000 | K9: 3000 | L9: 1000 | M9: 2500 | N9: =ROUND((F9*G9)+SUM(H9:M9), 0) | O9: 0.6 | P9: =ROUND(N9/(1-O9), -2) | Q9: =P9-N9 | R9: =Q9/P9 | S9: =ROUND(N9*1.35, -2) | T9: =(S9-N9)/S9
B10: 5 | C10: Tactical Cargo Pants | D10: Celana | E10: Cotton Ripstop | F10: 40000 | G10: 1.6 | H10: 42000 | I10: 8000 | J10: 3500 | K10: 3000 | L10: 1000 | M10: 3000 | N10: =ROUND((F10*G10)+SUM(H10:M10), 0) | O10: 0.6 | P10: =ROUND(N10/(1-O10), -2) | Q10: =P10-N10 | R10: =Q10/P10 | S10: =ROUND(N10*1.35, -2) | T10: =(S10-N10)/S10

Sheet Batch_Planner
B2: PERENCANAAN BATCH PRODUKSI & TITIK IMPAS (BEP)
B3: Alokasi Volume Batch, Rincian Biaya Tetap Peluncuran & Analisis Titik Impas (BEP)
B4: BAGIAN 1: ALOKASI RENCANA KUANTITI PRODUKSI SATU BATCH (DROP)
B5: No | C5: Nama Produk | D5: Target Qty (Pcs) | E5: HPP per Helai | F5: Total Modal Fisik | G5: Porsi Volume (%)
B6: 1 | C6: =HPP_Calculator!C6 | D6: 100 | E6: =HPP_Calculator!N6 | F6: =D6*E6 | G6: =D6/$D$11
B7: 2 | C7: =HPP_Calculator!C7 | D7: 100 | E7: =HPP_Calculator!N7 | F7: =D7*E7 | G7: =D7/$D$11
B8: 3 | C8: =HPP_Calculator!C8 | D8: 50 | E8: =HPP_Calculator!N8 | F8: =D8*E8 | G8: =D8/$D$11
B9: 4 | C9: =HPP_Calculator!C9 | D9: 40 | E9: =HPP_Calculator!N9 | F9: =D9*E9 | G9: =D9/$D$11
B10: 5 | C10: =HPP_Calculator!C10 | D10: 40 | E10: =HPP_Calculator!N10 | F10: =D10*E10 | G10: =D10/$D$11
B11: TOTAL MODAL FISIK BATCH | D11: =SUM(D6:D10) | F11: =SUM(F6:F10) | G11: =SUM(G6:G10)
B13: BAGIAN 2: BIAYA TETAP PELUNCURAN KOLEKSI (FIXED COSTS)
B14: Pembuatan Pola Mentah & Prototyping Sample | D14: Biaya jasa tukang pola & sample awal 5 produk | F14: 750000
B15: Sewa Studio & Model Foto Lookbook | D15: Sewa 1 shift studio foto & model katalog komersial | F15: 1800000
B16: Anggaran Iklan Digital (Meta/TikTok Ads) | D16: Anggaran ads berbayar untuk periode rilis 14 hari | F16: 1500000
B17: Seeding Influencer & Creator Gifting | D17: Biaya logistik & gift box khusus 10 kreator fesyen | F17: 600000
B18: Buffer Operasional & Lakban/Dus Cadangan | D18: Dana darurat operasional packing dan retur awal | F18: 350000
B19: TOTAL BIAYA TETAP PELUNCURAN | F19: =SUM(F14:F18)
B21: BAGIAN 3: ANALISIS TITIK IMPAS (BEP) & PROYEKSI LABA BATCH
B22: TOTAL MODAL INVESTASI BATCH (FISIK + BIAYA TETAP) | F22: =F11+F19
B23: Rata-Rata Margin Kotor Retail per Helai | F23: =AVERAGE(HPP_Calculator!Q6:Q10)
B24: Rata-Rata Harga Jual Retail Koleksi | F24: =AVERAGE(HPP_Calculator!P6:P10)
B25: TITIK IMPAS (BEP) DALAM UNIT HELAI | F25: =ROUNDUP(F19/F23, 0)
B26: TITIK IMPAS (BEP) DALAM OMZET PENJUALAN | F26: =F25*F24
B27: POTENSI OMZET MAKSIMAL (100% SOLD OUT) | F27: =SUMPRODUCT(D6:D10, HPP_Calculator!P6:P10)
B28: PROYEKSI LABA BERSIH BATCH (NET PROFIT) | F28: =F27-F22
B29: ESTIMASI ROI INVESTASI BATCH (%) | F29: =ROUND((F28/F22)*100, 1)

Sheet Vendor_Database
B2: DATABASE VENDOR & REKANAN PRODUKSI CLOTHING
B3: Katalog Mitra Kain, Konveksi Jahit, Sablon, Aksesoris & Packaging Terverifikasi
B4: No | C4: Nama Vendor / Toko | D4: Kategori Layanan | E4: Kontak / WhatsApp | F4: Kota / Lokasi | G4: Min. Order (MOQ) | H4: Lead Time (Hari) | I4: Catatan Kualitas & Keahlian
B5: 1 | C5: Kain Utama Tekstil | D5: Toko Bahan Kain | E5: 0812-8899-1122 | F5: Bandung | G5: 1 Roll (25 kg) | H5: 3 | I5: Spesialis Combed 16s/24s & Cotton Fleece reaktif.
B6: 2 | C6: Garment Kreasi Prima | D6: Konveksi Jahit | E6: 0813-7766-3344 | F6: Bandung | G6: 50 pcs per model | H6: 14 | I6: Jahitan rapi standar distro, overdeck 3 jarum & rantai.
B7: 3 | C7: Studio Sablon Pro | D7: Sablon Screenprint | E7: 0815-5544-2211 | F7: Tangerang | G7: 24 pcs per desain | H7: 7 | I7: Ahlian tinta Plastisol doff, Discharge & High-Density.
B8: 4 | C8: Woven Label Nusantara | D8: Label & Hangtag | E8: 0817-2233-9900 | F8: Jakarta Barat | G8: 100 lusin (1200 pcs) | H8: 10 | I8: Damask HD kerapatan benang tinggi, tidak gatal di leher.
B9: 5 | C9: Packbox Mandiri | D9: Kemasan Ziplock | E9: 0818-4455-6677 | F9: Surabaya | G9: 500 pcs | H9: 7 | I9: Ziplock frosted semi-buram dengan cetak sablon 1 warna.
B10: 6 | C10: Mitra Ekspedisi Kargo | D10: Logistik Distribusi | E10: 0819-3322-1100 | F10: Jakarta Pusat | G10: 10 kg | H10: 2 | I10: Tarif kargo ekonomis untuk pengiriman bahan antar kota.
